{"version": "4.5.6", "flags": {}, "shapes": [{"label": "dust_spot", "points": [[267.9476318359375, 103.8331298828125], [281.3462829589844, 117.307373046875]], "group_id": null, "shape_type": "rectangle", "flags": {}}, {"label": "dust_line", "points": [[1147.4520263671875, 522.6666259765625], [1161.8587646484375, 550.6328125]], "group_id": null, "shape_type": "rectangle", "flags": {}}, {"label": "dust_spot", "points": [[841.98388671875, 593.1383056640625], [853.398681640625, 603.1060791015625]], "group_id": null, "shape_type": "rectangle", "flags": {}}, {"label": "scratch", "points": [[0.0, 625.875732421875], [11.223602294921875, 669.97509765625]], "group_id": null, "shape_type": "rectangle", "flags": {}}, {"label": "dust_spot", "points": [[485.53802490234375, 402.637451171875], [492.7017822265625, 408.9239501953125]], "group_id": null, "shape_type": "rectangle", "flags": {}}, {"label": "dust_spot", "points": [[357.20001220703125, 745.199951171875], [368.4000244140625, 754.699951171875]], "group_id": null, "shape_type": "rectangle", "flags": {}}, {"label": "dust_spot", "points": [[1050.9163818359375, 29.982421875], [1060.7073974609375, 38.2332763671875]], "group_id": null, "shape_type": "rectangle", "flags": {}}], "imagePath": "b08_1_cam5_2.jpeg", "imageData": null, "imageHeight": 800, "imageWidth": 1333}