{"version": "4.5.6", "flags": {}, "shapes": [{"label": "dust_spot", "points": [[1203.943359375, 65.0252685546875], [1215.8272705078125, 76.6353759765625]], "group_id": null, "shape_type": "rectangle", "flags": {}}, {"label": "scratch", "points": [[858.536376953125, 45.5013427734375], [906.83056640625, 119.4124755859375]], "group_id": null, "shape_type": "rectangle", "flags": {}}, {"label": "dust_spot", "points": [[718.2685546875, 589.1025390625], [725.6817016601562, 598.3857421875]], "group_id": null, "shape_type": "rectangle", "flags": {}}, {"label": "dust_spot", "points": [[262.5025329589844, 152.8973388671875], [272.7851257324219, 162.6280517578125]], "group_id": null, "shape_type": "rectangle", "flags": {}}, {"label": "dust_line", "points": [[69.09097290039062, 671.35498046875], [116.71751403808594, 719.412353515625]], "group_id": null, "shape_type": "rectangle", "flags": {}}, {"label": "dust_spot", "points": [[176.61453247070312, 589.979248046875], [185.633544921875, 598.124267578125]], "group_id": null, "shape_type": "rectangle", "flags": {}}, {"label": "dust_spot", "points": [[162.05795288085938, 734.425048828125], [171.23727416992188, 742.858642578125]], "group_id": null, "shape_type": "rectangle", "flags": {}}, {"label": "dust_line", "points": [[197.88192749023438, 731.501708984375], [209.65536499023438, 756.983154296875]], "group_id": null, "shape_type": "rectangle", "flags": {}}, {"label": "spotlight", "points": [[612.0921630859375, 155.7020263671875], [637.370361328125, 182.197509765625]], "group_id": null, "shape_type": "rectangle", "flags": {}}, {"label": "dust_line", "points": [[289.0848083496094, 340.261474609375], [307.4593505859375, 358.812744140625]], "group_id": null, "shape_type": "rectangle", "flags": {}}, {"label": "dust_spot", "points": [[181.51028442382812, 232.873046875], [191.42562866210938, 242.9093017578125]], "group_id": null, "shape_type": "rectangle", "flags": {}}, {"label": "dust_spot", "points": [[227.2176513671875, 239.4027099609375], [237.13302612304688, 248.592529296875]], "group_id": null, "shape_type": "rectangle", "flags": {}}, {"label": "dust_spot", "points": [[249.95040893554688, 218.36279296875], [265.5489807128906, 230.333740234375]], "group_id": null, "shape_type": "rectangle", "flags": {}}, {"label": "scratch", "points": [[1285.251953125, 519.285400390625], [1314.557861328125, 529.568115234375]], "group_id": null, "shape_type": "rectangle", "flags": {}}, {"label": "scratch", "points": [[1153.3753662109375, 441.907470703125], [1185.509033203125, 455.789306640625]], "group_id": null, "shape_type": "rectangle", "flags": {}}, {"label": "dust_line", "points": [[1205.5731201171875, 775.07373046875], [1212.94921875, 791.518798828125]], "group_id": null, "shape_type": "rectangle", "flags": {}}], "imagePath": "b04_1_cam3_1.jpeg", "imageData": null, "imageHeight": 800, "imageWidth": 1333}