{"version": "4.5.6", "flags": {}, "shapes": [{"label": "scratch", "points": [[0.0, 309.430908203125], [6.490638732910156, 358.674072265625]], "group_id": null, "shape_type": "rectangle", "flags": {}}, {"label": "scratch", "points": [[269.4930419921875, 53.39111328125], [279.2120056152344, 103.30029296875]], "group_id": null, "shape_type": "rectangle", "flags": {}}, {"label": "scratch", "points": [[2.2755355834960938, 109.9180908203125], [10.093246459960938, 141.569091796875]], "group_id": null, "shape_type": "rectangle", "flags": {}}, {"label": "scratch", "points": [[0.0, 35.1517333984375], [1.0900344848632812, 56.8424072265625]], "group_id": null, "shape_type": "rectangle", "flags": {}}, {"label": "scratch", "points": [[98.0849609375, 71.7611083984375], [108.32475280761719, 106.681640625]], "group_id": null, "shape_type": "rectangle", "flags": {}}, {"label": "scratch", "points": [[328.5857849121094, 0.0], [375.33135986328125, 108.65087890625]], "group_id": null, "shape_type": "rectangle", "flags": {}}, {"label": "dust_spot", "points": [[467.8280029296875, 103.870361328125], [474.6756591796875, 110.212158203125]], "group_id": null, "shape_type": "rectangle", "flags": {}}, {"label": "dust_spot", "points": [[680.1361694335938, 21.2303466796875], [686.3873901367188, 26.628662109375]], "group_id": null, "shape_type": "rectangle", "flags": {}}, {"label": "dust_spot", "points": [[774.2526245117188, 204.3211669921875], [780.4327392578125, 211.3040771484375]], "group_id": null, "shape_type": "rectangle", "flags": {}}, {"label": "dust_spot", "points": [[685.1958618164062, 218.6546630859375], [691.3976440429688, 225.4853515625]], "group_id": null, "shape_type": "rectangle", "flags": {}}, {"label": "dust_line", "points": [[740.658447265625, 482.138671875], [785.0424194335938, 514.607666015625]], "group_id": null, "shape_type": "rectangle", "flags": {}}, {"label": "dust_spot", "points": [[342.8999938964844, 792.199951171875], [348.3255920410156, 799.151123046875]], "group_id": null, "shape_type": "rectangle", "flags": {}}, {"label": "dust_line", "points": [[466.56756591796875, 615.517578125], [477.37835693359375, 631.933837890625]], "group_id": null, "shape_type": "rectangle", "flags": {}}, {"label": "dust_line", "points": [[354.0, 613.39990234375], [364.29998779296875, 631.5]], "group_id": null, "shape_type": "rectangle", "flags": {}}, {"label": "dust_line", "points": [[1050.699951171875, 406.39990234375], [1057.4000244140625, 424.0]], "group_id": null, "shape_type": "rectangle", "flags": {}}, {"label": "dust_line", "points": [[1046.0999755859375, 426.89990234375], [1051.9000244140625, 437.89990234375]], "group_id": null, "shape_type": "rectangle", "flags": {}}, {"label": "scratch", "points": [[615.0330810546875, 430.2314453125], [625.281005859375, 447.917236328125]], "group_id": null, "shape_type": "rectangle", "flags": {}}, {"label": "dust_line", "points": [[249.54412841796875, 558.0966796875], [270.3421936035156, 566.440185546875]], "group_id": null, "shape_type": "rectangle", "flags": {}}, {"label": "dust_line", "points": [[1185.3343505859375, 179.189697265625], [1193.5338134765625, 210.5401611328125]], "group_id": null, "shape_type": "rectangle", "flags": {}}, {"label": "dust_line", "points": [[380.7184753417969, 450.833740234375], [389.1279602050781, 481.36376953125]], "group_id": null, "shape_type": "rectangle", "flags": {}}, {"label": "dust_line", "points": [[370.6000061035156, 684.800048828125], [376.79998779296875, 700.39990234375]], "group_id": null, "shape_type": "rectangle", "flags": {}}, {"label": "stain", "points": [[992.2862548828125, 259.660888671875], [1046.703125, 307.54052734375]], "group_id": null, "shape_type": "rectangle", "flags": {}}, {"label": "dust_line", "points": [[1219.072509765625, 708.1572265625], [1235.0338134765625, 727.38330078125]], "group_id": null, "shape_type": "rectangle", "flags": {}}, {"label": "dust_spot", "points": [[927.4210205078125, 29.5789794921875], [937.3458251953125, 41.007568359375]], "group_id": null, "shape_type": "rectangle", "flags": {}}, {"label": "dust_spot", "points": [[76.0, 158.4000244140625], [83.39999389648438, 165.4000244140625]], "group_id": null, "shape_type": "rectangle", "flags": {}}, {"label": "dust_spot", "points": [[91.5, 192.9000244140625], [98.10000610351562, 199.4000244140625]], "group_id": null, "shape_type": "rectangle", "flags": {}}, {"label": "dust_spot", "points": [[116.89999389648438, 213.9000244140625], [123.30000305175781, 220.5]], "group_id": null, "shape_type": "rectangle", "flags": {}}, {"label": "dust_spot", "points": [[276.9703063964844, 716.688232421875], [285.13861083984375, 725.59912109375]], "group_id": null, "shape_type": "rectangle", "flags": {}}], "imagePath": "a09_1_cam5_2.jpeg", "imageData": null, "imageHeight": 800, "imageWidth": 1333}